nb2pdf/__init__.py
nb2pdf/asyncio_patch.py
nb2pdf/filter_cells.py
nb2pdf/pdf.py
nb2pdf-0.6.2.data/scripts/nb2pdf
test/__init__.py
test/test_filtering.py
nb2pdf-0.6.2.dist-info/LICENSE
nb2pdf-0.6.2.dist-info/METADATA
nb2pdf-0.6.2.dist-info/WHEEL
nb2pdf-0.6.2.dist-info/top_level.txt
nb2pdf-0.6.2.dist-info/RECORD
