Metadata-Version: 2.1
Name: nb2pdf
Version: 0.6.2
Summary: Jupyter Notebook to PDF Converter
Home-page: https://github.com/ucbds-infra/nb2pdf
Author: Chris Pyles & Yanay Rosen
Author-email: ds-infra@berkeley.edu
License: BSD-3-Clause
Platform: UNKNOWN
Classifier: Programming Language :: Python :: 3
Classifier: License :: OSI Approved :: BSD License
Classifier: Operating System :: OS Independent
Requires-Dist: nbformat
Requires-Dist: nbpdfexport
Requires-Dist: codecov
Requires-Dist: IPython
